Workbook

Sheet Dados
A1: Dados da loja
A2: Como usar: altere só as células amarelas (texto azul). O resto é calculado.
A4: Vendas na maquininha (2026) | B4: Valor bruto | C4: Nº de vendas
A5: Janeiro | B5: 1454.6 | C5: 6
A6: Fevereiro | B6: 3404.8 | C6: 10
A7: Março | B7: 1329.9 | C7: 6
A8: Abril | B8: 612 | C8: 6
A9: Maio | B9: 1091 | C9: 6
A10: Total | B10: =SUM(B5:B9) -> 7892.3 | C10: =SUM(C5:C9) -> 34
A11: Média por mês | B11: =AVERAGE(B5:B9) -> 1578.46 | C11: =AVERAGE(C5:C9) -> 6.8
A12: Ticket médio (por venda) | B12: =IFERROR(B10/C10,0) -> 232.12647
A13: Vendas fora da maquininha por mês (dinheiro / Pix direto) | B13: 0
A14: Faturamento médio mensal considerado | B14: =B11+B13 -> 1578.46
A16: Custos fixos mensais | B16: Valor / mês | C16: Observação
A17: Água + luz | B17: 250 | C17: Informado: média de R$ 250/mês.
A18: DAS do MEI (comércio) | B18: 82.05 | C18: Estimativa: 5% do salário mínimo 2026 + R$ 1 de ICMS. Confirme no boleto.
A19: Aluguel da maquininha | B19: 0 | C19: A maquininha está na modalidade 'Aluguel'. Coloque o valor mensal cobrado.
A20: Viagens SP / Goiânia | B20: =5000/12 -> 416.66667 | C20: Informado: cerca de R$ 5.000 por ano, dividido por 12 meses.
A21: Outros (internet, sacolas, etiquetas, divulgação) | B21: 0 | C21: Preencher, se houver.
A22: Total custos fixos | B22: =SUM(B17:B21) -> 748.71667
A24: Taxas da maquininha (Visa) | B24: Taxa | C24: % das vendas (estimado)
A25: Pix na maquininha | B25: 0.0073 | C25: 0.2
A26: Débito | B26: 0.0199 | C26: 0.2
A27: Crédito à vista e parcelado até 4x | B27: 0.0449 | C27: 0.6
A28: Soma (deve dar 100%) | C28: =SUM(C25:C27) -> 1
A29: Taxa média por venda | B29: =SUMPRODUCT(B25:B27,C25:C27) -> 0.03238
A31: Lucro desejado (% do preço de venda) | B31: 0.2
A32: Multiplicador que ela usa hoje (ex.: 3 = triplica o custo) | B32: 3

Sheet Calculadora
A1: Calculadora de preço (markup divisor)
A2: Preço = Custo da peça ÷ [1 − (% custos fixos + % taxa do cartão + % lucro)]
A4: % custos fixos (fixos ÷ faturamento) | B4: =IFERROR(Dados!B22/Dados!B14,0) -> 0.47433363
A5: % taxa média do cartão | B5: =Dados!B29 -> 0.03238
A6: % lucro desejado | B6: =Dados!B31 -> 0.2
A7: Soma | B7: =SUM(B4:B6) -> 0.70671363
A8: Markup divisor (1 − soma) | B8: =1-B7 -> 0.29328637
A9: Multiplicador equivalente (1 ÷ divisor) | B9: =IF(B8<=0,"Inviável",1/B8) -> 3.4096368 | C9: =IF(B8<=0,"A soma passou de 100%: com esse faturamento, nenhum preço cobre custos + lucro.","")
A11: Custo da peça (já com frete) | B11: Preço sugerido (markup) | C11: Lucro por peça | D11: Preço se dobrar (x2) | E11: Preço x2,5 | F11: Preço do jeito atual
A12: 30 | B12: =IF($B$8<=0,"-",A12/$B$8) -> 102.28911 | C12: =IF($B$8<=0,"-",B12*$B$6) -> 20.457821 | D12: =A12*2 -> 60 | E12: =A12*2.5 -> 75 | F12: =A12*Dados!$B$32 -> 90
A13: 50 | B13: =IF($B$8<=0,"-",A13/$B$8) -> 170.48184 | C13: =IF($B$8<=0,"-",B13*$B$6) -> 34.096368 | D13: =A13*2 -> 100 | E13: =A13*2.5 -> 125 | F13: =A13*Dados!$B$32 -> 150
A14: 80 | B14: =IF($B$8<=0,"-",A14/$B$8) -> 272.77095 | C14: =IF($B$8<=0,"-",B14*$B$6) -> 54.554189 | D14: =A14*2 -> 160 | E14: =A14*2.5 -> 200 | F14: =A14*Dados!$B$32 -> 240
A15: 120 | B15: =IF($B$8<=0,"-",A15/$B$8) -> 409.15642 | C15: =IF($B$8<=0,"-",B15*$B$6) -> 81.831284 | D15: =A15*2 -> 240 | E15: =A15*2.5 -> 300 | F15: =A15*Dados!$B$32 -> 360
A16: 200 | B16: =IF($B$8<=0,"-",A16/$B$8) -> 681.92737 | C16: =IF($B$8<=0,"-",B16*$B$6) -> 136.38547 | D16: =A16*2 -> 400 | E16: =A16*2.5 -> 500 | F16: =A16*Dados!$B$32 -> 600

Sheet Simulação
A1: E se ela baixar o preço?
A2: Quanto ela precisa vender a mais para continuar ganhando o mesmo que hoje.
A4: Faturamento médio atual / mês | B4: =Dados!B14 -> 1578.46
A5: Custos fixos / mês | B5: =Dados!B22 -> 748.71667
A6: Taxa média do cartão | B6: =Dados!B29 -> 0.03238
A7: Multiplicador atual | B7: =Dados!B32 -> 3
A8: Margem de contribuição atual | B8: =1-1/B7-B6 -> 0.63428667
A9: Sobra para ela hoje / mês (lucro) | B9: =B4*B8-B5 -> 252.47947
A11: Cenário | B11: Multiplicador | C11: Preço muda em | D11: Margem de contribuição | E11: Ponto de equilíbrio / mês | F11: Faturamento p/ manter o lucro | G11: Peças vendidas a mais
A12: Do jeito atual | B12: =Dados!B32 -> 3 | C12: =B12/$B$7-1 -> 0 | D12: =1-1/B12-$B$6 -> 0.63428667 | E12: =IF(D12<=0,"-",$B$5/D12) -> 1180.4074 | F12: =IF(D12<=0,"-",($B$5+MAX($B$9,0))/D12) -> 1578.46 | G12: =IF(D12<=0,"-",(F12/$B$4)/(B12/$B$7)-1) -> 0
A13: Multiplicar por 2,5 | B13: 2.5 | C13: =B13/$B$7-1 -> -0.16666667 | D13: =1-1/B13-$B$6 -> 0.56762 | E13: =IF(D13<=0,"-",$B$5/D13) -> 1319.0456 | F13: =IF(D13<=0,"-",($B$5+MAX($B$9,0))/D13) -> 1763.8493 | G13: =IF(D13<=0,"-",(F13/$B$4)/(B13/$B$7)-1) -> 0.34093936
A14: Dobrar (x2) | B14: 2 | C14: =B14/$B$7-1 -> -0.33333333 | D14: =1-1/B14-$B$6 -> 0.46762 | E14: =IF(D14<=0,"-",$B$5/D14) -> 1601.122 | F14: =IF(D14<=0,"-",($B$5+MAX($B$9,0))/D14) -> 2141.0464 | G14: =IF(D14<=0,"-",(F14/$B$4)/(B14/$B$7)-1) -> 1.0346221
A15: Markup calculado | B15: =Calculadora!B9 -> 3.4096368 | C15: =B15/$B$7-1 -> 0.13654561 | D15: =1-1/B15-$B$6 -> 0.67433363 | E15: =IF(D15<=0,"-",$B$5/D15) -> 1110.306 | F15: =IF(D15<=0,"-",($B$5+MAX($B$9,0))/D15) -> 1484.7193 | G15: =IF(D15<=0,"-",(F15/$B$4)/(B15/$B$7)-1) -> -0.1723935
A17: Leitura: 'Peças vendidas a mais' = quantas peças a mais (em %) ela precisa vender por mês, com o preço novo, para ter a mesma sobra de hoje.
